chain_logging/__init__.py
chain_logging/base.py
chain_logging/fastapi.py
chain_logging/flask.py
chain_logging-0.1.9.dist-info/LICENSE
chain_logging-0.1.9.dist-info/METADATA
chain_logging-0.1.9.dist-info/WHEEL
chain_logging-0.1.9.dist-info/top_level.txt
chain_logging-0.1.9.dist-info/RECORD
