Metadata-Version: 2.1
Name: chain-logging
Version: 0.1.9
Summary: Chain Logger to distinct each request for Python Web Server (Support Flask and FastAPI) and looks like the logger is chained
Home-page: https://github.com/Danangjoyoo/chain-logging
Author: danangjoyoo (Agus Danangjoyo)
Author-email: <agus.danangjoyo.blog@gmail.com>
Keywords: fastapi,logging
Classifier: Development Status :: 5 - Production/Stable
Classifier: Intended Audience :: Developers
Classifier: Programming Language :: Python :: 3 :: Only
Classifier: Programming Language :: Python :: 3.7
Classifier: Programming Language :: Python :: 3.8
Classifier: Programming Language :: Python :: 3.9
Classifier: Programming Language :: Python :: 3.10
Classifier: Programming Language :: Python :: 3.11
Classifier: Environment :: Web Environment
Classifier: Operating System :: OS Independent
Classifier: Typing :: Typed
License-File: LICENSE
